{"title":"g102鼠标微动更换","description":"g102鼠标双击了，然后听说可以自己更换微动，所以就动手换了。","keywords":"g102,mouse,switch,double click","labels":["动手"],"date":"2021-08-09","path":"2021/08/mouse-switch.md","slug":"2021_08_mouse-switch","html":"<p>不久前，办公用的鼠标g102出现双击现象。一开始还不是很明显，后面在打开文件夹和写代码的时候比较影响，最主要的可感知到的问题是双击会选中代码光标所在的整个单词。</p>\n<p>遂网上搜索了一下g102双击的问题，一查发现这个是通病，好的话大概会过保才会双击。不好的话没几个月就会了，（这没过保的时候坏了更好吧。。。）。同时搜索到可以自行\n更换微动的方式解决这个问题，但需要焊锡工具。</p>\n<p>得勒，二话不说直接买。</p>\n<h3 id=\"工具\">工具</h3>\n<ol>\n<li>螺丝刀</li>\n<li>微动，价格8元</li>\n<li>电烙铁，价格8元</li>\n</ol>\n<h3 id=\"过程\">过程</h3>\n<p>拆开鼠标还是很容易，注意需要小心的是不要弄坏电路板。</p>\n<p><div style=\"text-align: center;\"><img align=\"center\" style=\"margin-bottom: 20px;border-radius: 8px;background: #f8fdf3;\" data-zoomable src=\"https://i.loli.net/2021/08/09/7vAPh1WydOteRTL.jpg\" alt=\"微动模块\" ></div></p>\n<p>主要的过程是需要小心翼翼的拆开微动模块，因为有三个焊锡点，所以需要细心处理。</p>\n<p>千万小心不要像我一样被烫伤。</p>\n<p>安装好后，可以先连上电脑试试可不可以再装回螺丝。</p>\n"}